kurye
