Metadata-Version: 1.1
Name: kurye
Version: 0.0.4
Summary: simple github cloner for boilerplate projects
Home-page: https://github.com/f/kurye
Author: Fatih Kadir Akin
Author-email: fka@fatihak.in
License: MIT
Keywords: github install clone
Platform: UNKNOWN
Classifier: Development Status :: 3 - Alpha
Classifier: Intended Audience :: Developers
